matpes/__init__.py
matpes/cli.py
matpes/data.py
matpes/db.py
matpes-0.0.3.dist-info/LICENSE
matpes-0.0.3.dist-info/METADATA
matpes-0.0.3.dist-info/WHEEL
matpes-0.0.3.dist-info/entry_points.txt
matpes-0.0.3.dist-info/top_level.txt
matpes-0.0.3.dist-info/RECORD
