Metadata-Version: 2.2
Name: matpes
Version: 0.0.3
Summary: Tools for working with MatPES.
Author-email: MatPES Development Team <ongsp@ucsd.edu>
Maintainer-email: Shyue Ping Ong <ongsp@ucsd.edu>
License: BSD-3-Clause
Keywords: potential energy surface,PES,VASP,analysis,crystal,materials,science,ai,ml
Classifier: Development Status :: 4 - Beta
Classifier: Intended Audience :: Science/Research
Classifier: License :: OSI Approved :: MIT License
Classifier: Operating System :: OS Independent
Classifier: Programming Language :: Python :: 3
Classifier: Programming Language :: Python :: 3.10
Classifier: Programming Language :: Python :: 3.11
Classifier: Programming Language :: Python :: 3.12
Classifier: Topic :: Scientific/Engineering :: Chemistry
Classifier: Topic :: Scientific/Engineering :: Information Analysis
Classifier: Topic :: Scientific/Engineering :: Physics
Requires-Python: <3.13,>=3.10
License-File: LICENSE
Requires-Dist: pandas>=2
Requires-Dist: pymongo>=4.11
Requires-Dist: pymatgen
Requires-Dist: tqdm
